my_custom_package_005/__init__.py
my_custom_package_005/m1/__init__.py
my_custom_package_005/m1/dtype_filters.py
my_custom_package_005/m1/word_frequency.py
my_custom_package_005-0.1.dist-info/LICENCE.txt
my_custom_package_005-0.1.dist-info/METADATA
my_custom_package_005-0.1.dist-info/WHEEL
my_custom_package_005-0.1.dist-info/top_level.txt
my_custom_package_005-0.1.dist-info/RECORD
